{
  "users": [
    {
      "id": 1,
      "first_name": "Hoang",
      "last_name": "Admin",
      "email": "admin@example.com",
      "password": "admin_pass",
      "profile_image": "/images/users/admin.jpg",
      "bio": "System administrator.",
      "status": "ACTIVE",
      "created_at": "2024-01-10T09:00:00",
      "updated_at": "2024-01-10T09:00:00",

      "roles": [
        {
          "id": 1,
          "role_name": "ROLE_ADMIN"
        }
      ],

      "subscriptions": [
        {
          "id": 1,
          "plan": "PREMIUM",
          "start_time": "2024-05-01T00:00:00",
          "end_time": "2025-05-01T00:00:00",
          "status": "ACTIVE"
        }
      ],

      "payments": [
        {
          "id": 1,
          "plan_id": 1,
          "transition_id": "TXN123456",
          "amount": 9.99,
          "payment_method": "PAYPAL",
          "payment_status": "COMPLETED",
          "payment_date": "2024-05-01T00:00:00"
        }
      ]
    },

    {
      "id": 2,
      "first_name": "Minh",
      "last_name": "Artist",
      "email": "artist@example.com",
      "password": "artist_pass",
      "profile_image": "/images/users/artist.jpg",
      "bio": "Music producer and songwriter.",
      "status": "ACTIVE",
      "created_at": "2024-02-12T10:00:00",
      "updated_at": "2024-02-12T10:00:00",

      "roles": [
        {
          "id": 2,
          "role_name": "ROLE_ARTIST"
        }
      ],

      "albums": [
        {
          "id": 1,
          "title": "Soobin Hoàng Sơn",
          "release_date": "2024-06-01T00:00:00",
          "cover_image": "/images/albums/soobin.jpg",
          "type": "FREE",

          "songs": [
            {
              "id": 1,
              "title": "Phía sau một cô gái",
              "duration": "00:03:25",
              "file_url": "/songs/phia-sau-mot-co-gai.mp3",
              "views": 5500,
              "genres": [
                { "id": 1, "genre_name": "Pop" },
                { "id": 2, "genre_name": "Acoustic" }
              ]
            },
            {
              "id": 2,
              "title": "Nếu ngày ấy",
              "duration": "00:04:10",
              "file_url": "/songs/neu-ngay-ay.mp3",
              "views": 3200,
              "genres": [
                { "id": 1, "genre_name": "Pop" }
              ]
            }
          ]
        }
      ]
    },

    {
      "id": 3,
      "first_name": "An",
      "last_name": "Customer",
      "email": "customer@example.com",
      "password": "customer_pass",
      "profile_image": "/images/users/customer.jpg",
      "bio": "Enjoys listening to pop music.",
      "status": "ACTIVE",
      "created_at": "2024-03-15T08:30:00",
      "updated_at": "2024-03-15T08:30:00",

      "roles": [
        {
          "id": 3,
          "role_name": "ROLE_USER"
        }
      ],

      "playlists": [
        {
          "id": 1,
          "name": "My Favorite Songs",
          "is_public": 1,
          "created_at": "2024-05-20T10:00:00",

          "songs": [
            {
              "id": 1,
              "title": "Phía sau một cô gái",
              "duration": "00:03:25"
            },
            {
              "id": 2,
              "title": "Nếu ngày ấy",
              "duration": "00:04:10"
            }
          ]
        }
      ],

      "wishlists": [
        {
          "song_id": 1,
          "title": "Soobin"
        }
      ],

      "song_histories": [
        {
          "song_id": 2,
          "played_at": "2024-05-22T12:00:00"
        }
      ],

      "downloads": [
        {
          "song_id": 1,
          "added_at": "2024-05-21T11:00:00"
        }
      ],

      "comments": [
        {
          "id": 1,
          "song_id": 1,
          "content": "Bài này chill thật sự!",
          "created_at": "2024-05-22T08:00:00",
          "parent_id": null
        }
      ]
    }
  ],

  "subscription_plan": [
    {
      "id": 1,
      "plan_name": "Premium",
      "price": 9.99,
      "duration_days": 30
    }
  ]
}